discord_msic/__init__.py
discord_msic/discord_toolkit.py
discord_misc-0.2.44.dist-info/METADATA
discord_misc-0.2.44.dist-info/WHEEL
discord_misc-0.2.44.dist-info/top_level.txt
discord_misc-0.2.44.dist-info/RECORD
